{
  "manolis": {
    "name": "Manolis Savva",
    "special": true
  },
  "pat": {
    "name": "Pat Hanrahan",
    "web": "http://graphics.stanford.edu/~hanrahan/"
  },
  "angel": {
    "name": "Angel X. Chang",
    "web": "https://angelxuanchang.github.io/"
  },
  "angie": {
    "name": "Angela Dai",
    "web": "http://graphics.stanford.edu/~adai/"
  },
  "matt": {
    "name": "Matthew Fisher",
    "web": "http://graphics.stanford.edu/~mdfisher/"
  },
  "matthias": {
    "name": "Matthias Nießner",
    "web": "http://graphics.stanford.edu/~niessner/"
  },
  "gilbert": {
    "name": "Gilbert Bernstein",
    "web": "http://graphics.stanford.edu/~gilbo/"
  },
  "chrisman": {
    "name": "Christopher D. Manning",
    "web": "http://nlp.stanford.edu/manning/"
  },
  "chrispotts": {
    "name": "Christopher Potts",
    "web": "http://web.stanford.edu/~cgpotts/"
  },
  "daniel": {
    "name": "Daniel Ritchie",
    "web": "https://dritchie.github.io/"
  },
  "tom": {
    "name": "Thomas Funkhouser",
    "web": "http://www.cs.princeton.edu/~funk/"
  },
  "maciej": {
    "name": "Maciej Halber",
    "web": "http://www.cs.princeton.edu/~mhalber/"
  },
  "leo": {
    "name": "Leonidas Guibas",
    "web": "http://geometry.stanford.edu/member/guibas/"
  },
  "hao": {
    "name": "Hao Su",
    "web": "http://ai.stanford.edu/~haosu/"
  },
  "eric": {
    "name": "Li Yi",
    "web": "http://geometry.stanford.edu/person.php?id=ericyi"
  },
  "qixing": {
    "name": "Qixing Huang",
    "web": "http://ttic.uchicago.edu/~huangqx/"
  },
  "zimo": {
    "name": "Zimo Li"
  },
  "silvio": {
    "name": "Silvio Savarese",
    "web": "http://cvgl.stanford.edu/silvio/"
  },
  "shuran": {
    "name": "Shuran Song",
    "web": "http://vision.princeton.edu/people/shurans/"
  },
  "andy": {
    "name": "Andy Zeng",
    "web": "http://www.cs.princeton.edu/~andyz/"
  },
  "jianxiong": {
    "name": "Jianxiong Xiao",
    "web": "http://vision.princeton.edu/people/xj/"
  },
  "fisher": {
    "name": "Fisher Yu",
    "web": "http://yf.io/"
  },
  "sanjay": {
    "name": "Sanjay Kairam",
    "web": "http://www.sanjaykairam.com/"
  },
  "diana": {
    "name": "Diana MacLean",
    "web": ""
  },
  "arti": {
    "name": "Arti Chhajta",
    "web": ""
  },
  "nickkong": {
    "name": "Nicholas Kong",
    "web": "http://www.eecs.berkeley.edu/~nkong/"
  },
  "jeff": {
    "name": "Jeffrey Heer",
    "web": "http://jheer.org/"
  },
  "maneesh": {
    "name": "Maneesh Agrawala",
    "web": "http://vis.berkeley.edu/~maneesh"
  },
  "feifei": {
    "name": "Li Fei-Fei",
    "web": "http://vision.stanford.edu/"
  },
  "will": {
    "name": "Will Monroe",
    "web": "http://www.stanford.edu/~wmonroe4/"
  },
  "yangyan": {
    "name": "Yangyan Li",
    "web": "http://web.stanford.edu/~yangyan/"
  },
  "yinda": {
    "name": "Yinda Zhang",
    "web": "http://robots.princeton.edu/people/yindaz/"
  },
  "ersin": {
    "name": "Ersin Yumer",
    "web": "http://www.meyumer.com/"
  },
  "jlee": {
    "name": "Joon-Young Lee",
    "web": "https://sites.google.com/site/jyleecv/"
  },
  "hjin": {
    "name": "Hailin Jin",
    "web": "https://research.adobe.com/person/hailin-jin/"
  },
  "ruizhen": {
    "name": "Ruizhen Hu",
    "web": "http://csse.szu.edu.cn/staff/ruizhenhu/"
  },
  "oliver": {
    "name": "Oliver van Kaick",
    "web": "http://people.scs.carleton.ca/~olivervankaick/"
  },
  "youyi": {
    "name": "Youyi Zheng",
    "web": "http://sist.shanghaitech.edu.cn/faculty/zhengyy/"
  },
  "mihail": {
    "name": "Mihail Eric",
    "web": "http://stanford.edu/~meric/"
  },
  "kyle": {
    "name": "Kyle Genova",
    "web": "http://3dvision.princeton.edu/people.html"
  },
  "lin": {
    "name": "Lin Shao",
    "web": "https://icme.stanford.edu/people/lin-shao"
  },
  "christiane": {
    "name": "Christiane Fellbaum",
    "web": "https://www.cs.princeton.edu/~fellbaum/"
  },
  "alexey": {
    "name": "Alexey Dosovitskiy",
    "web": "https://dosovits.github.io/"
  },
  "vladlen": {
    "name": "Vladlen Koltun",
    "web": "http://vladlen.info/"
  },
  "silvio": {
    "name": "Silvio Savarese",
    "web": "http://cvgl.stanford.edu/silvio/"
  },
  "rishi": {
    "name": "Rishi Mago"
  },
  "pranav": {
    "name": "Pranav Krishna"
  },
  "kai": {
    "name": "Kai Wang",
    "web": "https://kwang-ether.github.io"
  },
  "kevin": {
    "name": "Kevin Chen"
  },
  "chrischoy": {
    "name": "Christopher B. Choy",
    "web": "https://chrischoy.github.io/"
  },
  "yifeiShi": {
    "name": "Yifei Shi",
    "web": "http://www.yifeishi.net/"
  },
  "zhelunWu": {
    "name": "Zhelun Wu"
  },
  "kaiXu": {
    "name": "Kai Xu",
    "web": "https://kevinkaixu.net/"
  },
  "yuAnLin": {
    "name": "Yu-An Lin"
  },
  "benWeissmann": {
    "name": "Ben Weissmann"
  },
  "armenAvetisyan": {
    "name": "Armen Avetisyan",
    "web": "https://niessnerlab.org/members/armen_avetisyan/profile.html"
  },
  "manuelDahnert": {
    "name": "Manuel Dahnert",
    "web": "https://niessnerlab.org/members/manuel_dahnert/profile.html"
  },
  "peterAnderson": {
    "name": "Peter Anderson",
    "web": "https://www.panderson.me/"
  },
  "devendra": {
    "name": "Devendra Singh Chaplot",
    "web": "http://www.cs.cmu.edu/~dchaplot/"
  },
  "saurabh": {
    "name": "Saurabh Gupta",
    "web": "http://saurabhg.web.illinois.edu/"
  },
  "janaKosecka": {
    "name": "Jana Kosecka",
    "web": "https://cs.gmu.edu/~kosecka/"
  },
  "jitendra": {
    "name": "Jitendra Malik",
    "web": "https://people.eecs.berkeley.edu/~malik/"
  },
  "roozbeh": {
    "name": "Roozbeh Mottaghi",
    "web": "https://cs.stanford.edu/~roozbeh/"
  },
  "amirZamir": {
    "name": "Amir R. Zamir",
    "web": "https://cs.stanford.edu/~amirz/"
  },
  "abhishek": {
    "name": "Abhishek Kadian",
    "web": "https://abhiskk.github.io/"
  },
  "oleksandr": {
    "name": "Oleksandr Maksymets",
    "web": "https://research.fb.com/people/maksymets-oleksandr/"
  },
  "yili": {
    "name": "Yili Zhao",
    "web": "http://www.yilizhao.net/"
  },
  "erik": {
    "name": "Erik Wijmans",
    "web": "https://wijmans.xyz/"
  },
  "bhavana": {
    "name": "Bhavana Jain",
    "web": "https://github.com/bhavanajain"
  },
  "julian": {
    "name": "Julian Straub",
    "web": "http://people.csail.mit.edu/jstraub/"
  },
  "jia": {
    "name": "Jia Liu",
    "web": "https://www.linkedin.com/in/jia-liu-a1221a2"
  },
  "devi": {
    "name": "Devi Parikh",
    "web": "https://www.cc.gatech.edu/~parikh/"
  },
  "dhruv": {
    "name": "Dhruv Batra",
    "web": "https://www.cc.gatech.edu/~dbatra/"
  },
  "changan": {
    "name": "Changan Chen",
    "web": "https://changan.io/"
  },
  "sha": {
    "name": "Sha Hu",
    "web": "https://husha1993.github.io/"
  },
  "payam": {
    "name": "Payam Nikdel",
    "web": "http://payamn.github.io/"
  },
  "greg": {
    "name": "Greg Mori",
    "web": "https://www.cs.sfu.ca/~mori/"
  },
  "ari": {
    "name": "Ari Morcos",
    "web": "http://www.arimorcos.com/"
  },
  "stefan": {
    "name": "Stefan Lee",
    "web": "http://web.engr.oregonstate.edu/~leestef/"
  },
  "irfan": {
    "name": "Irfan Essa",
    "web": "http://www.irfanessa.gatech.edu/"
  },
  "joanne": {
    "name": "Joanne Truong",
    "web": "https://www.joannetruong.com/"
  },
  "aaron": {
    "name": "Aaron Gokaslan",
    "web": "https://skylion007.github.io/"
  },
  "alex": {
    "name": "Alexander Clegg",
    "web": "https://scholar.google.com/citations?user=p463opcAAAAJ&hl=en"
  },
  "soniaChernova": {
    "name": "Sonia Chernova",
    "web": "https://www.cc.gatech.edu/~chernova/"
  }
}
